ISL/cipher_bonus.v
// Módulo: cipher_bonus
// Descrição: Cifrador de BLOCO parametrizado com FSM de 4 estados.

module cipher_bonus #(
    parameter PLAINTEXT_WIDTH = 32,
    parameter KEY_WIDTH       = 8
)(
    input wire                            clk,
    input wire                            rst,
    input wire                            start,
    input wire  [KEY_WIDTH-1:0]           key,
    input wire  [PLAINTEXT_WIDTH-1:0]     plaintext,

    output wire                           done,
    output wire [PLAINTEXT_WIDTH-1:0]     ciphertext
);

    // Calcula a largura necessária para o contador de bits
    localparam COUNTER_WIDTH = $clog2(PLAINTEXT_WIDTH);

    // Definição dos estados da FSM
    parameter IDLE    = 2'b00;
    parameter LOAD    = 2'b01;
    parameter PROCESS = 2'b10;
    parameter DONE    = 2'b11;

    // Sinais internos
    reg [1:0]                       state, next_state;
    reg [COUNTER_WIDTH-1:0]         bit_counter;
    reg [KEY_WIDTH-1:0]             key_reg;
    reg [PLAINTEXT_WIDTH-1:0]       plaintext_reg;
    reg [PLAINTEXT_WIDTH-1:0]       ciphertext_reg;

    // Bloco 1: Lógica de Transição de Estados (Sequencial)
    always @(posedge clk or posedge rst) begin
        if (rst)
            state <= IDLE;
        else
            state <= next_state;
    end

    // Bloco 2: Lógica de Próximo Estado (Combinacional)
    always @(*) begin
        next_state = state;
        case (state)
            IDLE:     if (start) next_state = LOAD;
            LOAD:     next_state = PROCESS;
            PROCESS:  if (bit_counter == PLAINTEXT_WIDTH - 1) next_state = DONE;
            DONE:     if (!start) next_state = IDLE;
        endcase
    end

    // Bloco 3: Datapath (Lógica de processamento dos dados)
    always @(posedge clk or posedge rst) begin
        if (rst) begin
            bit_counter <= 0;
            ciphertext_reg <= 0;
        end else begin
            case (state)
                LOAD: begin
                    key_reg <= key;
                    plaintext_reg <= plaintext;
                    ciphertext_reg <= 0;
                    bit_counter <= 0;
                end
                PROCESS: begin
                    // Reutiliza a chave com o operador de módulo (%)
                    ciphertext_reg[bit_counter] <= plaintext_reg[bit_counter] ^ key_reg[bit_counter % KEY_WIDTH];
                    bit_counter <= bit_counter + 1;
                end
            endcase
        end
    end

    // Lógica de Saída
    assign ciphertext = ciphertext_reg;
    assign done = (state == DONE);

endmodule

ISL/cipher_bonus_tb.v
// Módulo: cipher_bonus_tb
`timescale 1ns/1ps

module cipher_bonus_tb;

    parameter PLAINTEXT_WIDTH = 32;
    parameter KEY_WIDTH       = 8;

    reg                               clk;
    reg                               rst;
    reg                               start;
    reg [KEY_WIDTH-1:0]               key;
    reg [PLAINTEXT_WIDTH-1:0]         plaintext;
    wire                              done;
    wire [PLAINTEXT_WIDTH-1:0]        ciphertext;

    integer     error_count = 0;
    reg [PLAINTEXT_WIDTH-1:0]         expected_ciphertext;

    cipher_bonus #(
        .PLAINTEXT_WIDTH(PLAINTEXT_WIDTH),
        .KEY_WIDTH(KEY_WIDTH)
    ) dut (
        .clk(clk),
        .rst(rst),
        .start(start),
        .key(key),
        .plaintext(plaintext),
        .done(done),
        .ciphertext(ciphertext)
    );

    always #5 clk = ~clk;

    initial begin
        $dumpfile("cipher_bonus_waveform.vcd");
        $dumpvars(0, dut);

        $display("Iniciando simulação final e definitiva...");
        clk = 0; rst = 1; start = 0;
        #30;
        rst = 0;
        
        for (integer test_num = 1; test_num <= 5; test_num = test_num + 1) begin
            $display("----------------------------------------");
            $display("Iniciando Teste Aleatório #%0d", test_num);
            
            wait (dut.done === 0);
            @(posedge clk);

            for (integer i = 0; i < KEY_WIDTH; i=i+32) key[i+:32] = $random;
            for (integer i = 0; i < PLAINTEXT_WIDTH; i=i+32) plaintext[i+:32] = $random;
            
            start <= 1;
            @(posedge clk);
            start <= 0;

            wait (dut.done === 1); 
            #1;
            
            for (integer i = 0; i < PLAINTEXT_WIDTH; i = i + 1) begin
                expected_ciphertext[i] = plaintext[i] ^ key[i % KEY_WIDTH];
            end
            
            if (ciphertext === expected_ciphertext) begin
                $display(">> SUCESSO!");
                $display("   Plaintext: %b", plaintext);
                $display("   Chave:     %b", key);
                $display("   Saída:     %b", ciphertext);
            end else begin
                $display(">> ERRO!");
                $display("   Plaintext: %b", plaintext);
                $display("   Chave:     %b", key);
                $display("   Obtido:    %b", ciphertext);
                $display("   Esperado:  %b", expected_ciphertext);
                error_count = error_count + 1;
            end
        end
        
        #50;

        $display("\n----------------------------------------");
        if (error_count == 0) $display(">> FIM: Todos os testes passaram!");
        else $display(">> FIM: %0d testes falharam.", error_count);
        $display("----------------------------------------");
        $finish;
    end

endmodule

ISL/cipher_bonus_waveform.vcd
$date
	Fri Jul  4 11:24:47 2025
$end
$version
	Icarus Verilog
$end
$timescale
	1ps
$end
$scope module cipher_bonus_tb $end
$scope module dut $end
$var wire 32 ! ciphertext [31:0] $end
$var wire 1 " clk $end
$var wire 8 # key [7:0] $end
$var wire 32 $ plaintext [31:0] $end
$var wire 1 % rst $end
$var wire 1 & start $end
$var wire 1 ' done $end
$var parameter 32 ( COUNTER_WIDTH $end
$var parameter 2 ) DONE $end
$var parameter 2 * IDLE $end
$var parameter 32 + KEY_WIDTH $end
$var parameter 2 , LOAD $end
$var parameter 32 - PLAINTEXT_WIDTH $end
$var parameter 2 . PROCESS $end
$var reg 5 / bit_counter [4:0] $end
$var reg 32 0 ciphertext_reg [31:0] $end
$var reg 8 1 key_reg [7:0] $end
$var reg 2 2 next_state [1:0] $end
$var reg 32 3 plaintext_reg [31:0] $end
$var reg 2 4 state [1:0] $end
$upscope $end
$upscope $end
$enddefinitions $end
$comment Show the parameter values. $end
$dumpall
b10 .
b100000 -
b1 ,
b1000 +
b0 *
b11 )
b101 (
$end
#0
$dumpvars
b0 4
bx 3
b0 2
bx 1
b0 0
b0 /
0'
0&
1%
bx $
bx #
0"
b0 !
$end
#5000
1"
#10000
0"
#15000
1"
#20000
0"
#25000
1"
#30000
0"
0%
#35000
b1 2
1&
b11000000100010010101111010000001 $
b100100 #
1"
#40000
0"
#45000
b10 2
b1 4
0&
1"
#50000
0"
#55000
b10 4
b11000000100010010101111010000001 3
b100100 1
1"
#60000
0"
#65000
b1 /
b1 !
b1 0
1"
#70000
0"
#75000
b10 /
1"
#80000
0"
#85000
b11 /
b101 !
b101 0
1"
#90000
0"
#95000
b100 /
1"
#100000
0"
#105000
b101 /
1"
#110000
0"
#115000
b110 /
b100101 !
b100101 0
1"
#120000
0"
#125000
b111 /
1"
#130000
0"
#135000
b1000 /
b10100101 !
b10100101 0
1"
#140000
0"
#145000
b1001 /
1"
#150000
0"
#155000
b1010 /
b1010100101 !
b1010100101 0
1"
#160000
0"
#165000
b1011 /
1"
#170000
0"
#175000
b1100 /
b101010100101 !
b101010100101 0
1"
#180000
0"
#185000
b1101 /
b1101010100101 !
b1101010100101 0
1"
#190000
0"
#195000
b1110 /
b11101010100101 !
b11101010100101 0
1"
#200000
0"
#205000
b1111 /
b111101010100101 !
b111101010100101 0
1"
#210000
0"
#215000
b10000 /
1"
#220000
0"
#225000
b10001 /
b10111101010100101 !
b10111101010100101 0
1"
#230000
0"
#235000
b10010 /
1"
#240000
0"
#245000
b10011 /
b1010111101010100101 !
b1010111101010100101 0
1"
#250000
0"
#255000
b10100 /
b11010111101010100101 !
b11010111101010100101 0
1"
#260000
0"
#265000
b10101 /
1"
#270000
0"
#275000
b10110 /
b1011010111101010100101 !
b1011010111101010100101 0
1"
#280000
0"
#285000
b10111 /
1"
#290000
0"
#295000
b11000 /
b101011010111101010100101 !
b101011010111101010100101 0
1"
#300000
0"
#305000
b11001 /
1"
#310000
0"
#315000
b11010 /
1"
#320000
0"
#325000
b11011 /
b100101011010111101010100101 !
b100101011010111101010100101 0
1"
#330000
0"
#335000
b11100 /
1"
#340000
0"
#345000
b11101 /
1"
#350000
0"
#355000
b11110 /
b100100101011010111101010100101 !
b100100101011010111101010100101 0
1"
#360000
0"
#365000
b11 2
b11111 /
b1100100101011010111101010100101 !
b1100100101011010111101010100101 0
1"
#370000
0"
#375000
b0 2
1'
b11 4
b0 /
b11100100101011010111101010100101 !
b11100100101011010111101010100101 0
1"
#380000
0"
#385000
0'
b0 4
1"
#390000
0"
#395000
b1 2
1&
b10110001111100000101011001100011 $
b1001 #
1"
#400000
0"
#405000
b10 2
b1 4
0&
1"
#410000
0"
#415000
b10 4
b0 !
b0 0
b10110001111100000101011001100011 3
b1001 1
1"
#420000
0"
#425000
b1 /
1"
#430000
0"
#435000
b10 /
b10 !
b10 0
1"
#440000
0"
#445000
b11 /
1"
#450000
0"
#455000
b100 /
b1010 !
b1010 0
1"
#460000
0"
#465000
b101 /
1"
#470000
0"
#475000
b110 /
b101010 !
b101010 0
1"
#480000
0"
#485000
b111 /
b1101010 !
b1101010 0
1"
#490000
0"
#495000
b1000 /
1"
#500000
0"
#505000
b1001 /
b101101010 !
b101101010 0
1"
#510000
0"
#515000
b1010 /
b1101101010 !
b1101101010 0
1"
#520000
0"
#525000
b1011 /
b11101101010 !
b11101101010 0
1"
#530000
0"
#535000
b1100 /
b111101101010 !
b111101101010 0
1"
#540000
0"
#545000
b1101 /
b1111101101010 !
b1111101101010 0
1"
#550000
0"
#555000
b1110 /
1"
#560000
0"
#565000
b1111 /
b101111101101010 !
b101111101101010 0
1"
#570000
0"
#575000
b10000 /
1"
#580000
0"
#585000
b10001 /
b10101111101101010 !
b10101111101101010 0
1"
#590000
0"
#595000
b10010 /
1"
#600000
0"
#605000
b10011 /
1"
#610000
0"
#615000
b10100 /
b10010101111101101010 !
b10010101111101101010 0
1"
#620000
0"
#625000
b10101 /
b110010101111101101010 !
b110010101111101101010 0
1"
#630000
0"
#635000
b10110 /
b1110010101111101101010 !
b1110010101111101101010 0
1"
#640000
0"
#645000
b10111 /
b11110010101111101101010 !
b11110010101111101101010 0
1"
#650000
0"
#655000
b11000 /
b111110010101111101101010 !
b111110010101111101101010 0
1"
#660000
0"
#665000
b11001 /
1"
#670000
0"
#675000
b11010 /
1"
#680000
0"
#685000
b11011 /
1"
#690000
0"
#695000
b11100 /
b1000111110010101111101101010 !
b1000111110010101111101101010 0
1"
#700000
0"
#705000
b11101 /
b11000111110010101111101101010 !
b11000111110010101111101101010 0
1"
#710000
0"
#715000
b11110 /
b111000111110010101111101101010 !
b111000111110010101111101101010 0
1"
#720000
0"
#725000
b11 2
b11111 /
1"
#730000
0"
#735000
b0 2
1'
b11 4
b0 /
b10111000111110010101111101101010 !
b10111000111110010101111101101010 0
1"
#740000
0"
#745000
0'
b0 4
1"
#750000
0"
#755000
b1 2
1&
b1000110110111111001100110001101 $
b1101 #
1"
#760000
0"
#765000
b10 2
b1 4
0&
1"
#770000
0"
#775000
b10 4
b0 !
b0 0
b1000110110111111001100110001101 3
b1101 1
1"
#780000
0"
#785000
b1 /
1"
#790000
0"
#795000
b10 /
1"
#800000
0"
#805000
b11 /
1"
#810000
0"
#815000
b100 /
1"
#820000
0"
#825000
b101 /
1"
#830000
0"
#835000
b110 /
1"
#840000
0"
#845000
b111 /
1"
#850000
0"
#855000
b1000 /
b10000000 !
b10000000 0
1"
#860000
0"
#865000
b1001 /
1"
#870000
0"
#875000
b1010 /
1"
#880000
0"
#885000
b1011 /
b10010000000 !
b10010000000 0
1"
#890000
0"
#895000
b1100 /
1"
#900000
0"
#905000
b1101 /
b1010010000000 !
b1010010000000 0
1"
#910000
0"
#915000
b1110 /
1"
#920000
0"
#925000
b1111 /
1"
#930000
0"
#935000
b10000 /
b1001010010000000 !
b1001010010000000 0
1"
#940000
0"
#945000
b10001 /
1"
#950000
0"
#955000
b10010 /
b101001010010000000 !
b101001010010000000 0
1"
#960000
0"
#965000
b10011 /
1"
#970000
0"
#975000
b10100 /
1"
#980000
0"
#985000
b10101 /
b100101001010010000000 !
b100101001010010000000 0
1"
#990000
0"
#995000
b10110 /
1"
#1000000
0"
#1005000
b10111 /
b10100101001010010000000 !
b10100101001010010000000 0
1"
#1010000
0"
#1015000
b11000 /
b110100101001010010000000 !
b110100101001010010000000 0
1"
#1020000
0"
#1025000
b11001 /
b1110100101001010010000000 !
b1110100101001010010000000 0
1"
#1030000
0"
#1035000
b11010 /
b11110100101001010010000000 !
b11110100101001010010000000 0
1"
#1040000
0"
#1045000
b11011 /
1"
#1050000
0"
#1055000
b11100 /
b1011110100101001010010000000 !
b1011110100101001010010000000 0
1"
#1060000
0"
#1065000
b11101 /
1"
#1070000
0"
#1075000
b11110 /
1"
#1080000
0"
#1085000
b11 2
b11111 /
b1001011110100101001010010000000 !
b1001011110100101001010010000000 0
1"
#1090000
0"
#1095000
b0 2
1'
b11 4
b0 /
1"
#1100000
0"
#1105000
0'
b0 4
1"
#1110000
0"
#1115000
b1 2
1&
b10001001001101110101001000010010 $
b1100101 #
1"
#1120000
0"
#1125000
b10 2
b1 4
0&
1"
#1130000
0"
#1135000
b10 4
b0 !
b0 0
b10001001001101110101001000010010 3
b1100101 1
1"
#1140000
0"
#1145000
b1 /
b1 !
b1 0
1"
#1150000
0"
#1155000
b10 /
b11 !
b11 0
1"
#1160000
0"
#1165000
b11 /
b111 !
b111 0
1"
#1170000
0"
#1175000
b100 /
1"
#1180000
0"
#1185000
b101 /
b10111 !
b10111 0
1"
#1190000
0"
#1195000
b110 /
b110111 !
b110111 0
1"
#1200000
0"
#1205000
b111 /
b1110111 !
b1110111 0
1"
#1210000
0"
#1215000
b1000 /
1"
#1220000
0"
#1225000
b1001 /
b101110111 !
b101110111 0
1"
#1230000
0"
#1235000
b1010 /
b1101110111 !
b1101110111 0
1"
#1240000
0"
#1245000
b1011 /
b11101110111 !
b11101110111 0
1"
#1250000
0"
#1255000
b1100 /
1"
#1260000
0"
#1265000
b1101 /
b1011101110111 !
b1011101110111 0
1"
#1270000
0"
#1275000
b1110 /
b11011101110111 !
b11011101110111 0
1"
#1280000
0"
#1285000
b1111 /
1"
#1290000
0"
#1295000
b10000 /
1"
#1300000
0"
#1305000
b10001 /
1"
#1310000
0"
#1315000
b10010 /
b100011011101110111 !
b100011011101110111 0
1"
#1320000
0"
#1325000
b10011 /
1"
#1330000
0"
#1335000
b10100 /
1"
#1340000
0"
#1345000
b10101 /
b100100011011101110111 !
b100100011011101110111 0
1"
#1350000
0"
#1355000
b10110 /
1"
#1360000
0"
#1365000
b10111 /
b10100100011011101110111 !
b10100100011011101110111 0
1"
#1370000
0"
#1375000
b11000 /
1"
#1380000
0"
#1385000
b11001 /
1"
#1390000
0"
#1395000
b11010 /
1"
#1400000
0"
#1405000
b11011 /
b100010100100011011101110111 !
b100010100100011011101110111 0
1"
#1410000
0"
#1415000
b11100 /
b1100010100100011011101110111 !
b1100010100100011011101110111 0
1"
#1420000
0"
#1425000
b11101 /
1"
#1430000
0"
#1435000
b11110 /
b101100010100100011011101110111 !
b101100010100100011011101110111 0
1"
#1440000
0"
#1445000
b11 2
b11111 /
b1101100010100100011011101110111 !
b1101100010100100011011101110111 0
1"
#1450000
0"
#1455000
b0 2
1'
b11 4
b0 /
b11101100010100100011011101110111 !
b11101100010100100011011101110111 0
1"
#1460000
0"
#1465000
0'
b0 4
1"
#1470000
0"
#1475000
b1 2
1&
b110110101111100110100001101 $
b1 #
1"
#1480000
0"
#1485000
b10 2
b1 4
0&
1"
#1490000
0"
#1495000
b10 4
b0 !
b0 0
b110110101111100110100001101 3
b1 1
1"
#1500000
0"
#1505000
b1 /
1"
#1510000
0"
#1515000
b10 /
1"
#1520000
0"
#1525000
b11 /
b100 !
b100 0
1"
#1530000
0"
#1535000
b100 /
b1100 !
b1100 0
1"
#1540000
0"
#1545000
b101 /
1"
#1550000
0"
#1555000
b110 /
1"
#1560000
0"
#1565000
b111 /
1"
#1570000
0"
#1575000
b1000 /
1"
#1580000
0"
#1585000
b1001 /
1"
#1590000
0"
#1595000
b1010 /
1"
#1600000
0"
#1605000
b1011 /
b10000001100 !
b10000001100 0
1"
#1610000
0"
#1615000
b1100 /
b110000001100 !
b110000001100 0
1"
#1620000
0"
#1625000
b1101 /
1"
#1630000
0"
#1635000
b1110 /
1"
#1640000
0"
#1645000
b1111 /
b100110000001100 !
b100110000001100 0
1"
#1650000
0"
#1655000
b10000 /
b1100110000001100 !
b1100110000001100 0
1"
#1660000
0"
#1665000
b10001 /
1"
#1670000
0"
#1675000
b10010 /
b101100110000001100 !
b101100110000001100 0
1"
#1680000
0"
#1685000
b10011 /
b1101100110000001100 !
b1101100110000001100 0
1"
#1690000
0"
#1695000
b10100 /
1"
#1700000
0"
#1705000
b10101 /
b101101100110000001100 !
b101101100110000001100 0
1"
#1710000
0"
#1715000
b10110 /
1"
#1720000
0"
#1725000
b10111 /
b10101101100110000001100 !
b10101101100110000001100 0
1"
#1730000
0"
#1735000
b11000 /
b110101101100110000001100 !
b110101101100110000001100 0
1"
#1740000
0"
#1745000
b11001 /
b1110101101100110000001100 !
b1110101101100110000001100 0
1"
#1750000
0"
#1755000
b11010 /
b11110101101100110000001100 !
b11110101101100110000001100 0
1"
#1760000
0"
#1765000
b11011 /
b111110101101100110000001100 !
b111110101101100110000001100 0
1"
#1770000
0"
#1775000
b11100 /
1"
#1780000
0"
#1785000
b11101 /
1"
#1790000
0"
#1795000
b11110 /
1"
#1800000
0"
#1805000
b11 2
b11111 /
1"
#1810000
0"
#1815000
b0 2
1'
b11 4
b0 /
1"
#1820000
0"
#1825000
0'
b0 4
1"
