ISL/cipher.v
// Módulo: cipher
// Descrição: Implementa uma cifra XOR sequencial de 8 bits.

module cipher(
    // Entradas
    input wire          clk,
    input wire          rst,
    input wire          start,
    input wire  [7:0]   key,
    input wire  [7:0]   plaintext,

    // Saídas
    output wire         done,
    output wire [7:0]   ciphertext
);

    // Definição dos estados da FSM
    parameter IDLE    = 2'b00;
    parameter LOAD    = 2'b01;
    parameter PROCESS = 2'b10;
    parameter DONE    = 2'b11;

    // Sinais internos
    reg [1:0]   state, next_state;
    reg [2:0]   bit_counter;
    reg [7:0]   key_reg;
    reg [7:0]   plaintext_reg;
    reg [7:0]   ciphertext_reg;

    // Bloco 1: Lógica de Transição de Estados (Sequencial)
    // Responsável apenas por atualizar o estado atual no pulso de clock.
    always @(posedge clk or posedge rst) begin
        if (rst)
            state <= IDLE;
        else
            state <= next_state;
    end

    // Bloco 2: Lógica de Próximo Estado (Combinacional)
    // Define qual será o próximo estado baseado no estado atual e nas entradas.
    always @(*) begin
        next_state = state;
        case (state)
            IDLE: begin
                if (start)
                    next_state = LOAD;
            end
            LOAD: begin
                next_state = PROCESS;
            end
            PROCESS: begin
                if (bit_counter == 3'd7) 
                    next_state = DONE;
            end
            DONE: begin
                if (!start) 
                    next_state = IDLE;
            end
        endcase
    end

    // Bloco 3: Lógica de Saída e Datapath (Sequencial)
    // Gerencia os registradores, o contador e as saídas.
    always @(posedge clk or posedge rst) begin
        if (rst) begin
            bit_counter <= 3'b0;
            ciphertext_reg <= 8'b0;
        end else begin
            case (state)
                LOAD: begin
                    key_reg <= key;
                    plaintext_reg <= plaintext;
                    ciphertext_reg <= 8'b0; 
                    bit_counter <= 3'b0;    
                end
                PROCESS: begin
                    // Executa o XOR para o bit atual e incrementa o contador
                    ciphertext_reg[bit_counter] <= plaintext_reg[bit_counter] ^ key_reg[bit_counter];
                    bit_counter <= bit_counter + 1;
                end
            endcase
        end
    end

    // Atribuições de saída contínuas
    assign ciphertext = ciphertext_reg;
    assign done = (state == DONE);

endmodule

ISL/cipher_tb.v
// Módulo: cipher_tb
// Descrição: Testbench robusto que exibe os resultados em formato BINÁRIO.
`timescale 1ns/1ps

module cipher_tb_robust_binary;

    // Sinais para conectar ao módulo
    reg         clk;
    reg         rst;
    reg         start;
    reg [7:0]   key;
    reg [7:0]   plaintext;
    wire        done;
    wire [7:0]  ciphertext;

    // Variáveis de controle do testbench
    integer     test_count = 0;
    integer     error_count = 0;
    reg [7:0]   expected_ciphertext;

    // Instanciação do Módulo sob Teste (DUT)
    cipher dut (
        .clk(clk),
        .rst(rst),
        .start(start),
        .key(key),
        .plaintext(plaintext),
        .done(done),
        .ciphertext(ciphertext)
    );

    // Geração do Clock
    always #5 clk = ~clk; // Clock de 100MHz (período de 10ns)

    // Task para executar um único ciclo de teste e verificar o resultado
    task run_test(input [7:0] test_key, input [7:0] test_plaintext);
    begin
        test_count = test_count + 1;
        $display("----------------------------------------");
        $display("Iniciando Teste %0d", test_count);
        
        key = test_key;
        plaintext = test_plaintext;
        
        start = 1;
        #10;
        start = 0;

        wait(done); 
        
        expected_ciphertext = test_plaintext ^ test_key;
        
        $display("Operação Concluída:");
        $display("  Texto Claro: 8'b%b", test_plaintext);
        $display("  Chave:       8'b%b", test_key);
        $display("  Resultado Esperado:   8'b%b", expected_ciphertext);
        $display("  Resultado Obtido:     8'b%b", ciphertext);
        
        if (ciphertext === expected_ciphertext) begin
            $display(">> Resultado: CORRETO!");
        end else begin
            $display(">> Resultado: INCORRETO!");
            error_count = error_count + 1;
        end
        #20;
    end
    endtask

    // Sequência Principal de Teste
    initial begin
        // --- Inicialização ---
        $dumpfile("cipher_waveform.vcd");
        $dumpvars(0, dut);
        $display("Iniciando simulação robusta...");
        clk = 0;
        rst = 1;
        start = 0;
        key = 8'h00;
        plaintext = 8'h00;
        #20;
        rst = 0;
        $display("Reset liberado.\n");
        #10;

        // --- Casos de Teste Específicos ---
        run_test(8'b10100101, 8'b00111111); // A5, 3F
        run_test(8'b11111111, 8'b11000011); // FF, C3

        // --- Casos de Teste de Borda (Edge Cases) ---
        $display("\n--- Iniciando Testes de Borda ---");
        run_test(8'b00000000, 8'b11001100); // 00, CC
        run_test(8'b01011010, 8'b00000000); // 5A, 00
        run_test(8'b11111111, 8'b10110100); // FF, B4
        run_test(8'b01111110, 8'b01111110); // 7E, 7E

        // --- Testes Aleatórios ---
        $display("\n--- Iniciando Testes Aleatórios ---");
        repeat (5) begin 
            run_test($random, $random);
        end

        // --- Relatório Final ---
        $display("\n----------------------------------------");
        $display("Relatório Final da Simulação:");
        if (error_count == 0) begin
            $display(">> SUCESSO! Todos os %0d testes passaram!", test_count);
        end else begin
            $display(">> FALHA! %0d de %0d testes falharam.", error_count, test_count);
        end
        $display("----------------------------------------");
        
        $finish;
    end

endmodule

ISL/cipher_waveform.vcd
$date
	Thu Jul  3 16:30:33 2025
$end
$version
	Icarus Verilog
$end
$timescale
	1ps
$end
$scope module cipher_tb_robust_binary $end
$scope module dut $end
$var wire 8 ! ciphertext [7:0] $end
$var wire 1 " clk $end
$var wire 8 # key [7:0] $end
$var wire 8 $ plaintext [7:0] $end
$var wire 1 % rst $end
$var wire 1 & start $end
$var wire 1 ' done $end
$var parameter 2 ( DONE $end
$var parameter 2 ) IDLE $end
$var parameter 2 * LOAD $end
$var parameter 2 + PROCESS $end
$var reg 3 , bit_counter [2:0] $end
$var reg 8 - ciphertext_reg [7:0] $end
$var reg 8 . key_reg [7:0] $end
$var reg 2 / next_state [1:0] $end
$var reg 8 0 plaintext_reg [7:0] $end
$var reg 2 1 state [1:0] $end
$upscope $end
$upscope $end
$enddefinitions $end
$comment Show the parameter values. $end
$dumpall
b10 +
b1 *
b0 )
b11 (
$end
#0
$dumpvars
b0 1
bx 0
b0 /
bx .
b0 -
b0 ,
0'
0&
1%
b0 $
b0 #
0"
b0 !
$end
#5000
1"
#10000
0"
#15000
1"
#20000
0"
0%
#25000
1"
#30000
b1 /
0"
1&
b111111 $
b10100101 #
#35000
b10 /
b1 1
1"
#40000
b10 /
0"
0&
#45000
b111111 0
b10100101 .
b10 1
1"
#50000
0"
#55000
b1 ,
1"
#60000
0"
#65000
b10 ,
b10 !
b10 -
1"
#70000
0"
#75000
b11 ,
1"
#80000
0"
#85000
b100 ,
b1010 !
b1010 -
1"
#90000
0"
#95000
b101 ,
b11010 !
b11010 -
1"
#100000
0"
#105000
b110 ,
1"
#110000
0"
#115000
b11 /
b111 ,
1"
#120000
0"
#125000
b0 /
b0 ,
b10011010 !
b10011010 -
1'
b11 1
1"
#130000
0"
#135000
0'
b0 1
1"
#140000
0"
#145000
b1 1
b10 /
1"
1&
b11000011 $
b11111111 #
#150000
0"
#155000
b10 1
b0 !
b0 -
b11000011 0
b11111111 .
b10 /
1"
0&
#160000
0"
#165000
b1 ,
1"
#170000
0"
#175000
b10 ,
1"
#180000
0"
#185000
b11 ,
b100 !
b100 -
1"
#190000
0"
#195000
b100 ,
b1100 !
b1100 -
1"
#200000
0"
#205000
b101 ,
b11100 !
b11100 -
1"
#210000
0"
#215000
b110 ,
b111100 !
b111100 -
1"
#220000
0"
#225000
b11 /
b111 ,
1"
#230000
0"
#235000
b0 /
1'
b11 1
b0 ,
1"
#240000
0"
#245000
0'
b0 1
1"
#250000
0"
#255000
b1 1
b10 /
1"
1&
b11001100 $
b0 #
#260000
0"
#265000
b0 !
b0 -
b11001100 0
b0 .
b10 1
b10 /
1"
0&
#270000
0"
#275000
b1 ,
1"
#280000
0"
#285000
b10 ,
1"
#290000
0"
#295000
b11 ,
b100 !
b100 -
1"
#300000
0"
#305000
b100 ,
b1100 !
b1100 -
1"
#310000
0"
#315000
b101 ,
1"
#320000
0"
#325000
b110 ,
1"
#330000
0"
#335000
b11 /
b111 ,
b1001100 !
b1001100 -
1"
#340000
0"
#345000
b0 /
b0 ,
b11001100 !
b11001100 -
1'
b11 1
1"
#350000
0"
#355000
0'
b0 1
1"
#360000
0"
#365000
b1 1
b10 /
1"
1&
b0 $
b1011010 #
#370000
0"
#375000
b10 1
b0 !
b0 -
b0 0
b1011010 .
b10 /
1"
0&
#380000
0"
#385000
b1 ,
1"
#390000
0"
#395000
b10 ,
b10 !
b10 -
1"
#400000
0"
#405000
b11 ,
1"
#410000
0"
#415000
b100 ,
b1010 !
b1010 -
1"
#420000
0"
#425000
b101 ,
b11010 !
b11010 -
1"
#430000
0"
#435000
b110 ,
1"
#440000
0"
#445000
b11 /
b111 ,
b1011010 !
b1011010 -
1"
#450000
0"
#455000
b0 /
1'
b11 1
b0 ,
1"
#460000
0"
#465000
0'
b0 1
1"
#470000
0"
#475000
b1 1
b10 /
1"
1&
b10110100 $
b11111111 #
#480000
0"
#485000
b0 !
b0 -
b10110100 0
b11111111 .
b10 1
b10 /
1"
0&
#490000
0"
#495000
b1 ,
b1 !
b1 -
1"
#500000
0"
#505000
b10 ,
b11 !
b11 -
1"
#510000
0"
#515000
b11 ,
1"
#520000
0"
#525000
b100 ,
b1011 !
b1011 -
1"
#530000
0"
#535000
b101 ,
1"
#540000
0"
#545000
b110 ,
1"
#550000
0"
#555000
b11 /
b111 ,
b1001011 !
b1001011 -
1"
#560000
0"
#565000
b0 /
b0 ,
1'
b11 1
1"
#570000
0"
#575000
0'
b0 1
1"
#580000
0"
#585000
b1 1
b10 /
1"
1&
b1111110 $
b1111110 #
#590000
0"
#595000
b10 1
b0 !
b0 -
b1111110 0
b1111110 .
b10 /
1"
0&
#600000
0"
#605000
b1 ,
1"
#610000
0"
#615000
b10 ,
1"
#620000
0"
#625000
b11 ,
1"
#630000
0"
#635000
b100 ,
1"
#640000
0"
#645000
b101 ,
1"
#650000
0"
#655000
b110 ,
1"
#660000
0"
#665000
b11 /
b111 ,
1"
#670000
0"
#675000
b0 /
1'
b11 1
b0 ,
1"
#680000
0"
#685000
0'
b0 1
1"
#690000
0"
#695000
b1 1
b10 /
1"
1&
b10000001 $
b100100 #
#700000
0"
#705000
b10000001 0
b100100 .
b10 1
b10 /
1"
0&
#710000
0"
#715000
b1 ,
b1 !
b1 -
1"
#720000
0"
#725000
b10 ,
1"
#730000
0"
#735000
b11 ,
b101 !
b101 -
1"
#740000
0"
#745000
b100 ,
1"
#750000
0"
#755000
b101 ,
1"
#760000
0"
#765000
b110 ,
b100101 !
b100101 -
1"
#770000
0"
#775000
b11 /
b111 ,
1"
#780000
0"
#785000
b0 /
b0 ,
b10100101 !
b10100101 -
1'
b11 1
1"
#790000
0"
#795000
0'
b0 1
1"
#800000
0"
#805000
b1 1
b10 /
1"
1&
b1100011 $
b1001 #
#810000
0"
#815000
b10 1
b0 !
b0 -
b1100011 0
b1001 .
b10 /
1"
0&
#820000
0"
#825000
b1 ,
1"
#830000
0"
#835000
b10 ,
b10 !
b10 -
1"
#840000
0"
#845000
b11 ,
1"
#850000
0"
#855000
b100 ,
b1010 !
b1010 -
1"
#860000
0"
#865000
b101 ,
1"
#870000
0"
#875000
b110 ,
b101010 !
b101010 -
1"
#880000
0"
#885000
b11 /
b111 ,
b1101010 !
b1101010 -
1"
#890000
0"
#895000
b0 /
1'
b11 1
b0 ,
1"
#900000
0"
#905000
0'
b0 1
1"
#910000
0"
#915000
b1 1
b10 /
1"
1&
b10001101 $
b1101 #
#920000
0"
#925000
b0 !
b0 -
b10001101 0
b1101 .
b10 1
b10 /
1"
0&
#930000
0"
#935000
b1 ,
1"
#940000
0"
#945000
b10 ,
1"
#950000
0"
#955000
b11 ,
1"
#960000
0"
#965000
b100 ,
1"
#970000
0"
#975000
b101 ,
1"
#980000
0"
#985000
b110 ,
1"
#990000
0"
#995000
b11 /
b111 ,
1"
#1000000
0"
#1005000
b0 /
b0 ,
b10000000 !
b10000000 -
1'
b11 1
1"
#1010000
0"
#1015000
0'
b0 1
1"
#1020000
0"
#1025000
b1 1
b10 /
1"
1&
b10010 $
b1100101 #
#1030000
0"
#1035000
b10 1
b0 !
b0 -
b10010 0
b1100101 .
b10 /
1"
0&
#1040000
0"
#1045000
b1 ,
b1 !
b1 -
1"
#1050000
0"
#1055000
b10 ,
b11 !
b11 -
1"
#1060000
0"
#1065000
b11 ,
b111 !
b111 -
1"
#1070000
0"
#1075000
b100 ,
1"
#1080000
0"
#1085000
b101 ,
b10111 !
b10111 -
1"
#1090000
0"
#1095000
b110 ,
b110111 !
b110111 -
1"
#1100000
0"
#1105000
b11 /
b111 ,
b1110111 !
b1110111 -
1"
#1110000
0"
#1115000
b0 /
1'
b11 1
b0 ,
1"
#1120000
0"
#1125000
0'
b0 1
1"
#1130000
0"
#1135000
b1 1
b10 /
1"
1&
b1101 $
b1 #
#1140000
0"
#1145000
b0 !
b0 -
b1101 0
b1 .
b10 1
b10 /
1"
0&
#1150000
0"
#1155000
b1 ,
1"
#1160000
0"
#1165000
b10 ,
1"
#1170000
0"
#1175000
b11 ,
b100 !
b100 -
1"
#1180000
0"
#1185000
b100 ,
b1100 !
b1100 -
1"
#1190000
0"
#1195000
b101 ,
1"
#1200000
0"
#1205000
b110 ,
1"
#1210000
0"
#1215000
b11 /
b111 ,
1"
#1220000
0"
#1225000
b0 /
b0 ,
1'
b11 1
1"
#1230000
0"
#1235000
0'
b0 1
1"
